{"id":"style.css","dependencies":[{"name":"_css_loader","parent":"/Users/jeanetteobrien/LocalRepo/transloc-challenge/style.css","resolved":"/usr/local/lib/node_modules/parcel-bundler/src/builtins/css-loader.js"}],"generated":{"css":"h1 {\n  font-family: Arial, Helvetica, sans-serif;\n  color: tomato;\n}\n\n#mapid {\n  height: 580px;\n}\n","js":"\nvar reloadCSS = require('_css_loader');\nmodule.hot.dispose(reloadCSS);\nmodule.hot.accept(reloadCSS);"},"hash":"6474efdeefcec3da725371a21654d7d7","cacheData":{"env":{}}}